bigquery_connector/__init__.py
bigquery_connector/connector.py
simple_bigquery_gcf_sync-0.1.0.dist-info/LICENSE
simple_bigquery_gcf_sync-0.1.0.dist-info/METADATA
simple_bigquery_gcf_sync-0.1.0.dist-info/WHEEL
simple_bigquery_gcf_sync-0.1.0.dist-info/top_level.txt
simple_bigquery_gcf_sync-0.1.0.dist-info/RECORD
