Metadata-Version: 2.1
Name: simple-bigquery-gcf-sync
Version: 0.1.0
Summary: A BigQuery connector for easy data syncing for your custom import. Checks the last date in the table and only appends new data or creates a new table. Made for Google Cloud Functions.
Home-page: https://github.com/carbonemys/simple-bigquery-gcf-sync
Author: Carbonemys
Author-email: carbonemys@carbonemys.nl
Classifier: Programming Language :: Python :: 3
Classifier: License :: OSI Approved :: MIT License
Classifier: Operating System :: OS Independent
Requires-Python: >=3.6
License-File: LICENSE
Requires-Dist: google-auth
Requires-Dist: google-cloud-bigquery
Requires-Dist: pandas
